lawkpyaibox/__init__.py
lawkpyaibox/datapipe/__init__.py
lawkpyaibox/datapipe/audio_extractor.py
lawkpyaibox/datapipe/audio_recorder.py
lawkpyaibox/datapipe/datathread.py
lawkpyaibox/datapipe/jsonop.py
lawkpyaibox/datapipe/print_log.py
lawkpyaibox/datapipe/search_target_extfile.py
lawkpyaibox/datapipe/video_editor.py
lawkpyaibox/osspipe/__init__.py
lawkpyaibox/osspipe/mysqlrds_manager.py
lawkpyaibox/osspipe/ossmanager.py
lawkpyaibox/osspipe/redis_manager.py
lawkpyaibox/service_boardx/__init__.py
lawkpyaibox/service_boardx/service_boardx.py
lawkpyaibox-0.0.8.dist-info/METADATA
lawkpyaibox-0.0.8.dist-info/WHEEL
lawkpyaibox-0.0.8.dist-info/top_level.txt
lawkpyaibox-0.0.8.dist-info/RECORD
