Metadata-Version: 2.1
Name: lawkpyaibox
Version: 0.0.8
Summary: python工具包，用于快速递归搜索文件路径、管理oss、快速读取和操作json、合并视频等
Home-page: https://gitlab.com/lawk_metaos/metaos_facear/pyaibox
Author: yingzhi
Author-email: jackhenry1992@gmail.com
License: apache 3.0
Requires: numpy
Requires: matplotlib
Requires: os
Requires: pyaudio
Requires: moviepy
Requires: jsonpath
